Metadata-Version: 2.1
Name: python-lambda
Version: 11.7.1
Summary: The bare minimum for a Python app running on Amazon Lambda.
Home-page: https://github.com/nficano/python-lambda
Author: Nick Ficano
Author-email: nficano@gmail.com
License: ISCL
Platform: UNKNOWN
Classifier: Development Status :: 2 - Pre-Alpha
Classifier: Intended Audience :: Developers
Classifier: License :: OSI Approved :: ISC License (ISCL)
Classifier: Natural Language :: English
Classifier: Programming Language :: Python :: 3.5
Classifier: Programming Language :: Python :: 3.6
Classifier: Programming Language :: Python :: 3.7
Classifier: Programming Language :: Python :: 3.8
Requires-Dist: boto3 (==1.4.4)
Requires-Dist: click (==6.6)
Requires-Dist: PyYAML (==5.1)
